[{"ContainerToolsException.Message":"in \"/Users/seanbarlow/Documents/GitHub/green-garden/green-garden-water-api/docker-compose.yml\", line 15, column 7","ContainerToolsException.ErrorCode":"DT1001","ContainerToolsException.StackTrace":"  at Microsoft.Docker.DockerComposeClient.ExecuteAsync (System.String options, System.String commandWithArguments, Microsoft.Docker.IDockerLogger logger, System.Threading.CancellationToken cancellationToken) [0x00104] in <e80c0b4673f5401aafafddae781d6dd2>:0 \n  at Microsoft.Docker.DockerComposeClient+MergedDockerComposeDocument.GetContentsFromDockerComposeConfigAsync (Microsoft.Docker.DockerComposeClient+CachedComposeConfigFilePaths cachedFilePaths, System.String hashOfFilesToBeMerged, System.Func`3[T1,T2,TResult] executeCommandAsync) [0x0007b] in <e80c0b4673f5401aafafddae781d6dd2>:0 \n  at Microsoft.Docker.DockerComposeClient+MergedDockerComposeDocument.EnsureContentsExistAsync (System.Func`3[T1,T2,TResult] executeCommandAsync) [0x0010f] in <e80c0b4673f5401aafafddae781d6dd2>:0 \n  at Microsoft.Docker.DockerComposeClient+MergedDockerComposeDocument.GetDockerComposeDocumentAsync (System.Func`3[T1,T2,TResult] executeCommandAsync) [0x00068] in <e80c0b4673f5401aafafddae781d6dd2>:0 \n  at Microsoft.Docker.DockerComposeClient.GetDockerComposeDocumentAsync (Microsoft.Docker.DockerComposeFileSet composeFileSet, Microsoft.Docker.DockerDevelopmentMode dockerDevelopmentMode, Microsoft.Docker.IDockerLogger logger, System.Threading.CancellationToken cancellationToken) [0x0014a] in <e80c0b4673f5401aafafddae781d6dd2>:0 \n  at Microsoft.Docker.DockerWorkspace.GetDockerServiceProfilesAsync (Microsoft.Docker.DockerDevelopmentMode dockerDevelopmentMode, Microsoft.Docker.IDockerLogger logger, System.Threading.CancellationToken cancellationToken) [0x000a3] in <e80c0b4673f5401aafafddae781d6dd2>:0 \n  at Microsoft.Docker.BuildTasks.GetServiceReferences.ExecuteCoreAsync (Microsoft.Docker.BuildTasks.DockerBuildTaskContext context) [0x0013b] in <508dda57951d4967b97ebcf6502c12b7>:0 \n  at Microsoft.Docker.BuildTasks.DockerBuildTask.ExecuteAsync (Microsoft.Docker.BuildTasks.DockerBuildTaskContext context) [0x0008c] in <508dda57951d4967b97ebcf6502c12b7>:0 ","ContainerToolsException.HResult":"-2146233088","ContainerToolsException.CommandLine.Program":"docker-compose","ContainerToolsException.CommandLine.TelemetrySafeArguments":"","ContainerToolsException.CommandLine.ExitCode":"1","ContainerToolsException.CommandLine.ErrorOutput":"yaml.parser.ParserError: while parsing a block mapping\n  in \"/Users/seanbarlow/Documents/GitHub/green-garden/green-garden-water-api/docker-compose.yml\", line 13, column 5\nexpected <block end>, but found '<block sequence start>'\n  in \"/Users/seanbarlow/Documents/GitHub/green-garden/green-garden-water-api/docker-compose.yml\", line 15, column 7"},{"ContainerToolsException.Message":"Service 'green-garden-water-api-dapr' uses the network stack of service 'green-garden-web-api' which is undefined.","ContainerToolsException.ErrorCode":"DT1001","ContainerToolsException.StackTrace":"  at Microsoft.Docker.DockerComposeClient.ExecuteAsync (System.String options, System.String commandWithArguments, Microsoft.Docker.IDockerLogger logger, System.Threading.CancellationToken cancellationToken) [0x00104] in <e80c0b4673f5401aafafddae781d6dd2>:0 \n  at Microsoft.Docker.DockerComposeClient+MergedDockerComposeDocument.GetContentsFromDockerComposeConfigAsync (Microsoft.Docker.DockerComposeClient+CachedComposeConfigFilePaths cachedFilePaths, System.String hashOfFilesToBeMerged, System.Func`3[T1,T2,TResult] executeCommandAsync) [0x0007b] in <e80c0b4673f5401aafafddae781d6dd2>:0 \n  at Microsoft.Docker.DockerComposeClient+MergedDockerComposeDocument.EnsureContentsExistAsync (System.Func`3[T1,T2,TResult] executeCommandAsync) [0x0010f] in <e80c0b4673f5401aafafddae781d6dd2>:0 \n  at Microsoft.Docker.DockerComposeClient+MergedDockerComposeDocument.GetDockerComposeDocumentAsync (System.Func`3[T1,T2,TResult] executeCommandAsync) [0x00068] in <e80c0b4673f5401aafafddae781d6dd2>:0 \n  at Microsoft.Docker.DockerComposeClient.GetDockerComposeDocumentAsync (Microsoft.Docker.DockerComposeFileSet composeFileSet, Microsoft.Docker.DockerDevelopmentMode dockerDevelopmentMode, Microsoft.Docker.IDockerLogger logger, System.Threading.CancellationToken cancellationToken) [0x0014a] in <e80c0b4673f5401aafafddae781d6dd2>:0 \n  at Microsoft.Docker.DockerWorkspace.GetDockerServiceProfilesAsync (Microsoft.Docker.DockerDevelopmentMode dockerDevelopmentMode, Microsoft.Docker.IDockerLogger logger, System.Threading.CancellationToken cancellationToken) [0x000a3] in <e80c0b4673f5401aafafddae781d6dd2>:0 \n  at Microsoft.Docker.BuildTasks.GetServiceReferences.ExecuteCoreAsync (Microsoft.Docker.BuildTasks.DockerBuildTaskContext context) [0x0013b] in <508dda57951d4967b97ebcf6502c12b7>:0 \n  at Microsoft.Docker.BuildTasks.DockerBuildTask.ExecuteAsync (Microsoft.Docker.BuildTasks.DockerBuildTaskContext context) [0x0008c] in <508dda57951d4967b97ebcf6502c12b7>:0 ","ContainerToolsException.HResult":"-2146233088","ContainerToolsException.CommandLine.Program":"docker-compose","ContainerToolsException.CommandLine.TelemetrySafeArguments":"","ContainerToolsException.CommandLine.ExitCode":"1","ContainerToolsException.CommandLine.ErrorOutput":"Service 'green-garden-water-api-dapr' uses the network stack of service 'green-garden-web-api' which is undefined."},{"ContainerToolsException.Message":"Service 'green-garden-water-api-dapr' depends on service 'green-garden-web-api' which is undefined.","ContainerToolsException.ErrorCode":"DT1001","ContainerToolsException.StackTrace":"  at Microsoft.Docker.DockerComposeClient.ExecuteAsync (System.String options, System.String commandWithArguments, Microsoft.Docker.IDockerLogger logger, System.Threading.CancellationToken cancellationToken) [0x00104] in <e80c0b4673f5401aafafddae781d6dd2>:0 \n  at Microsoft.Docker.DockerComposeClient+MergedDockerComposeDocument.GetContentsFromDockerComposeConfigAsync (Microsoft.Docker.DockerComposeClient+CachedComposeConfigFilePaths cachedFilePaths, System.String hashOfFilesToBeMerged, System.Func`3[T1,T2,TResult] executeCommandAsync) [0x0007b] in <e80c0b4673f5401aafafddae781d6dd2>:0 \n  at Microsoft.Docker.DockerComposeClient+MergedDockerComposeDocument.EnsureContentsExistAsync (System.Func`3[T1,T2,TResult] executeCommandAsync) [0x0010f] in <e80c0b4673f5401aafafddae781d6dd2>:0 \n  at Microsoft.Docker.DockerComposeClient+MergedDockerComposeDocument.GetDockerComposeDocumentAsync (System.Func`3[T1,T2,TResult] executeCommandAsync) [0x00068] in <e80c0b4673f5401aafafddae781d6dd2>:0 \n  at Microsoft.Docker.DockerComposeClient.GetDockerComposeDocumentAsync (Microsoft.Docker.DockerComposeFileSet composeFileSet, Microsoft.Docker.DockerDevelopmentMode dockerDevelopmentMode, Microsoft.Docker.IDockerLogger logger, System.Threading.CancellationToken cancellationToken) [0x0014a] in <e80c0b4673f5401aafafddae781d6dd2>:0 \n  at Microsoft.Docker.DockerWorkspace.GetDockerServiceProfilesAsync (Microsoft.Docker.DockerDevelopmentMode dockerDevelopmentMode, Microsoft.Docker.IDockerLogger logger, System.Threading.CancellationToken cancellationToken) [0x000a3] in <e80c0b4673f5401aafafddae781d6dd2>:0 \n  at Microsoft.Docker.BuildTasks.GetServiceReferences.ExecuteCoreAsync (Microsoft.Docker.BuildTasks.DockerBuildTaskContext context) [0x0013b] in <508dda57951d4967b97ebcf6502c12b7>:0 \n  at Microsoft.Docker.BuildTasks.DockerBuildTask.ExecuteAsync (Microsoft.Docker.BuildTasks.DockerBuildTaskContext context) [0x0008c] in <508dda57951d4967b97ebcf6502c12b7>:0 ","ContainerToolsException.HResult":"-2146233088","ContainerToolsException.CommandLine.Program":"docker-compose","ContainerToolsException.CommandLine.TelemetrySafeArguments":"","ContainerToolsException.CommandLine.ExitCode":"1","ContainerToolsException.CommandLine.ErrorOutput":"Service 'green-garden-water-api-dapr' depends on service 'green-garden-web-api' which is undefined."}]